biosparse/__init__.py
biosparse/_binding/__init__.py
biosparse/_binding/_cffi.py
biosparse/_binding/_span.py
biosparse/_binding/_sparse.py
biosparse/_binding/libbiosparse.so
biosparse/_numba/__init__.py
biosparse/_numba/_boxing.py
biosparse/_numba/_conversions.py
biosparse/_numba/_ffi.py
biosparse/_numba/_iterators.py
biosparse/_numba/_models.py
biosparse/_numba/_operators.py
biosparse/_numba/_overloads.py
biosparse/_numba/_types.py
biosparse/_numba/_validation.py
biosparse/kernel/__init__.py
biosparse/kernel/hvg.py
biosparse/kernel/mmd.py
biosparse/kernel/mwu.py
biosparse/kernel/ttest.py
biosparse/kernel/math/__init__.py
biosparse/kernel/math/_descriptive.py
biosparse/kernel/math/_mwu.py
biosparse/kernel/math/_regression.py
biosparse/kernel/math/_stats.py
biosparse/kernel/math/_tdist.py
biosparse/kernel/math/_ttest.py
biosparse/optim/__init__.py
biosparse/optim/_intrinsics.py
biosparse/optim/_ir_processor.py
biosparse/optim/_jit.py
biosparse/optim/_logging.py
biosparse/optim/_loop_hints.py
biosparse-0.1.1.dist-info/licenses/LICENSE
rust/convert.rs
rust/ffi.rs
rust/lib.rs
rust/slice.rs
rust/span.rs
rust/sparse.rs
rust/stack.rs
rust/storage.rs
rust/tools.rs
rust/transpose.rs
biosparse-0.1.1.dist-info/METADATA
biosparse-0.1.1.dist-info/WHEEL
biosparse-0.1.1.dist-info/top_level.txt
biosparse-0.1.1.dist-info/RECORD
