Metadata-Version: 2.4
Name: biosparse
Version: 0.1.1
Summary: High-performance sparse matrix computation library for bioinformatics
Author: biosparse contributors
License: MIT
Project-URL: Homepage, https://github.com/krkawzq/biosparse
Project-URL: Documentation, https://github.com/krkawzq/biosparse#readme
Project-URL: Repository, https://github.com/krkawzq/biosparse
Project-URL: Issues, https://github.com/krkawzq/biosparse/issues
Keywords: sparse,matrix,bioinformatics,single-cell,numba,high-performance
Classifier: Development Status :: 4 - Beta
Classifier: Intended Audience :: Science/Research
Classifier: License :: OSI Approved :: MIT License
Classifier: Operating System :: OS Independent
Classifier: Programming Language :: Python :: 3
Classifier: Programming Language :: Python :: 3.10
Classifier: Programming Language :: Python :: 3.11
Classifier: Programming Language :: Python :: 3.12
Classifier: Programming Language :: Python :: 3.13
Classifier: Programming Language :: Python :: 3.14
Classifier: Programming Language :: Rust
Classifier: Topic :: Scientific/Engineering :: Bio-Informatics
Requires-Python: >=3.10
License-File: LICENSE
Requires-Dist: cffi>=1.14.0
Requires-Dist: numba>=0.56.0
Requires-Dist: numpy>=1.21.0
Requires-Dist: scipy>=1.7.0
Provides-Extra: dev
Requires-Dist: pytest>=9.0.2; extra == "dev"
Dynamic: license-file
